djhost/__init__.py
djhost/middleware.py
djhost/version.py
djhost-0.0.2.dist-info/METADATA
djhost-0.0.2.dist-info/WHEEL
djhost-0.0.2.dist-info/top_level.txt
djhost-0.0.2.dist-info/RECORD
